{"cameraMode":{"drawMode":0,"name":"Shaded","section":"Shading Mode"},"sceneLighting":true,"audioPlay":false,"sceneViewState":{"m_AlwaysRefresh":false,"showFog":true,"showSkybox":true,"showFlares":true,"showImageEffects":true,"showParticleSystems":true,"showVisualEffectGraphs":true,"m_FxEnabled":true},"in2DMode":false,"pivot":{"x":1014.2340087890625,"y":557.6641235351563,"z":487.3287048339844},"rotation":{"x":-0.014378335326910019,"y":0.04018305614590645,"z":0.000582622189540416,"w":0.999116837978363},"size":836.747802734375,"orthographic":false}